sequence_rcgn/seqrec_2.v
module SeqRec_2_minseok (
	input		nRESET, CLK, X,
	output		Z
);

reg [2:0] shiftReg;
wire [3:0] tmp;

assign tmp[3:0] = {shiftReg[2:0], X};

always @(negedge nRESET or posedge CLK) 
begin
	if (~nRESET) begin
		shiftReg[2:0] <= 3'b000;
	end
	else begin
		shiftReg[2:0] <= tmp[2:0];
	end
end
assign Z = (tmp[3:0] == 4'b1101);
endmodule

sequence_rcgn/tb_seqrec_2.v
`timescale 1ns/10ps

module tb_seqrec;

reg rnRESET, rCLK, rX;
wire wZ;

SeqRec_2_minseok seqrec0(.nRESET(rnRESET), .CLK(rCLK), .X(rX), .Z(wZ));

always
begin
  #500 rCLK <= ~rCLK;
end

initial
begin
	$dumpfile("test2.vcd");
	$dumpvars(0, tb_seqrec);
	rCLK <= 1'b1;
	rnRESET <= 1'b0;
	rX <= 1'b0;
	#100 rnRESET <= 1'b1;
	#1000 rX <= 1'b1;
	#1000 rX <= 1'b1;
	#1000 rX <= 1'b0;
	#1000 rX <= 1'b0;
	#1000 rX <= 1'b1;
	#1000 rX <= 1'b1;
	#1000 rX <= 1'b0;
	#1000 rX <= 1'b1; // Z=1
	#1000 rX <= 1'b1;
	#1000 rX <= 1'b0;
	#1000 rX <= 1'b1; // Z=1
	#1000 rX <= 1'b0;
	#1000 rX <= 1'b1;
end

initial
begin
	$monitor("t=$3d rCLK=%d rX=%d wZ=%d \n",$time,rCLK,rX,wZ);
end
endmodule

sequence_rcgn/test.vcd
$date
	Mon Jun 11 19:56:25 2018
$end
$version
	Icarus Verilog
$end
$timescale
	10ps
$end
$scope module tb_seqrec $end
$var wire 1 ! wZ $end
$var reg 1 " rCLK $end
$var reg 1 # rX $end
$var reg 1 $ rnRESET $end
$scope module seqrec0 $end
$var wire 1 " CLK $end
$var wire 1 # X $end
$var wire 1 $ nRESET $end
$var wire 4 % tmp [3:0] $end
$var wire 1 ! Z $end
$var reg 3 & shiftReg [2:0] $end
$upscope $end
$upscope $end
$enddefinitions $end
#0
$dumpvars
b0 &
b0 %
0$
0#
1"
0!
$end
#10000
1$
#50000
0"
#100000
1"
#110000
b1 %
1#
#150000
0"
#200000
b11 %
b1 &
1"
#250000
0"
#300000
b111 %
b11 &
1"
#310000
b110 %
0#
#350000
0"
#400000
b1100 %
b110 &
1"
#450000
0"
#500000
b1000 %
b100 &
1"
#510000
b1001 %
1#
#550000
0"
#600000
b11 %
b1 &
1"
#650000
0"
#700000
b111 %
b11 &
1"
#710000
b110 %
0#
#750000
0"
#800000
b1100 %
b110 &
1"
#810000
1!
b1101 %
1#
#850000
0"
#900000
0!
b1011 %
b101 &
1"
#950000
0"
#1000000
b111 %
b11 &
1"
#1010000
b110 %
0#
#1050000
0"
#1100000
b1100 %
b110 &
1"
#1110000
1!
b1101 %
1#
#1150000
0"
#1200000
0!
b1011 %
b101 &
1"
#1210000
b1010 %
0#
#1250000
0"
#1300000
b100 %
b10 &
1"
#1310000
b101 %
1#
#1350000
0"
#1400000
b1011 %
b101 &
1"
#1450000
0"
#1500000
b111 %
b11 &
1"
#1550000
0"
#1600000
b1111 %
b111 &
1"
